{
  "data": {
    "article": {},
    "attachments": {},
    "author_id": "1684547487460388864",
    "conversation_id": "2070733389687292094",
    "created_at": "2026-06-27T12:49:04.000Z",
    "edit_controls": {
      "editable_until": "2026-06-27T13:49:04.000Z",
      "edits_remaining": 5,
      "is_edit_eligible": false
    },
    "edit_history_tweet_ids": [
      "2070851910723318111"
    ],
    "entities": {
      "mentions": [
        {
          "end": 16,
          "id": "1666276925474746371",
          "start": 0,
          "username": "Jason4028172723"
        }
      ]
    },
    "geo": {},
    "id": "2070851910723318111",
    "in_reply_to_user_id": "1666276925474746371",
    "lang": "ja",
    "note_tweet": {
      "entities": {}
    },
    "possibly_sensitive": false,
    "public_metrics": {
      "bookmark_count": 0,
      "impression_count": 0,
      "like_count": 0,
      "quote_count": 0,
      "reply_count": 0,
      "retweet_count": 0
    },
    "referenced_tweets": [
      {
        "id": "2070733389687292094",
        "type": "replied_to"
      }
    ],
    "reply_settings": "everyone",
    "text": "@Jason4028172723 恭喜！"
  },
  "includes": {
    "media": [
      {
        "height": 1536,
        "media_key": "3_2070733142487715840",
        "public_metrics": {},
        "type": "photo",
        "url": "https://pbs.twimg.com/media/HLy40mab0AAUbb5.jpg",
        "width": 2048
      },
      {
        "height": 2048,
        "media_key": "3_2070733142475067392",
        "public_metrics": {},
        "type": "photo",
        "url": "https://pbs.twimg.com/media/HLy40mXa0AA5PVN.jpg",
        "width": 1536
      },
      {
        "height": 1536,
        "media_key": "3_2070733141246083072",
        "public_metrics": {},
        "type": "photo",
        "url": "https://pbs.twimg.com/media/HLy40hyaAAAxPkt.jpg",
        "width": 2048
      }
    ],
    "tweets": [
      {
        "article": {},
        "attachments": {},
        "author_id": "1684547487460388864",
        "conversation_id": "2070733389687292094",
        "created_at": "2026-06-27T12:49:04.000Z",
        "edit_controls": {
          "editable_until": "2026-06-27T13:49:04.000Z",
          "edits_remaining": 5,
          "is_edit_eligible": false
        },
        "edit_history_tweet_ids": [
          "2070851910723318111"
        ],
        "entities": {
          "mentions": [
            {
              "end": 16,
              "id": "1666276925474746371",
              "start": 0,
              "username": "Jason4028172723"
            }
          ]
        },
        "geo": {},
        "id": "2070851910723318111",
        "in_reply_to_user_id": "1666276925474746371",
        "lang": "ja",
        "note_tweet": {
          "entities": {}
        },
        "possibly_sensitive": false,
        "public_metrics": {
          "bookmark_count": 0,
          "impression_count": 0,
          "like_count": 0,
          "quote_count": 0,
          "reply_count": 0,
          "retweet_count": 0
        },
        "referenced_tweets": [
          {
            "id": "2070733389687292094",
            "type": "replied_to"
          }
        ],
        "reply_settings": "everyone",
        "text": "@Jason4028172723 恭喜！"
      },
      {
        "article": {},
        "attachments": {
          "media_keys": [
            "3_2070733142487715840",
            "3_2070733142475067392",
            "3_2070733141246083072"
          ]
        },
        "author_id": "1666276925474746371",
        "conversation_id": "2070733389687292094",
        "created_at": "2026-06-27T04:58:07.000Z",
        "edit_controls": {
          "editable_until": "2026-06-27T05:58:07.000Z",
          "edits_remaining": 5,
          "is_edit_eligible": true
        },
        "edit_history_tweet_ids": [
          "2070733389687292094"
        ],
        "entities": {
          "urls": [
            {
              "display_url": "pic.x.com/0NzArg3Nwk",
              "end": 44,
              "expanded_url": "https://x.com/Jason4028172723/status/2070733389687292094/photo/1",
              "media_key": "3_2070733142487715840",
              "start": 21,
              "url": "https://t.co/0NzArg3Nwk"
            },
            {
              "display_url": "pic.x.com/0NzArg3Nwk",
              "end": 44,
              "expanded_url": "https://x.com/Jason4028172723/status/2070733389687292094/photo/1",
              "media_key": "3_2070733142475067392",
              "start": 21,
              "url": "https://t.co/0NzArg3Nwk"
            },
            {
              "display_url": "pic.x.com/0NzArg3Nwk",
              "end": 44,
              "expanded_url": "https://x.com/Jason4028172723/status/2070733389687292094/photo/1",
              "media_key": "3_2070733141246083072",
              "start": 21,
              "url": "https://t.co/0NzArg3Nwk"
            }
          ]
        },
        "geo": {},
        "id": "2070733389687292094",
        "lang": "zh",
        "note_tweet": {
          "entities": {}
        },
        "possibly_sensitive": false,
        "public_metrics": {
          "bookmark_count": 0,
          "impression_count": 6661,
          "like_count": 73,
          "quote_count": 0,
          "reply_count": 17,
          "retweet_count": 0
        },
        "reply_settings": "everyone",
        "text": "盼星星盼月亮终于到了！SIOC我来力！🥰 https://t.co/0NzArg3Nwk"
      }
    ],
    "users": [
      {
        "created_at": "2023-07-27T12:54:09.000Z",
        "description": "",
        "entities": {
          "url": {
            "urls": [
              {
                "display_url": "me_twi.trtt.net",
                "end": 23,
                "expanded_url": "https://me_twi.trtt.net",
                "start": 0,
                "url": "https://t.co/bm8bpeI3fN"
              }
            ]
          }
        },
        "id": "1684547487460388864",
        "name": "青空 しょな",
        "profile_image_url": "https://pbs.twimg.com/profile_images/2040417468221620224/AJg3v3Jf_normal.jpg",
        "protected": false,
        "public_metrics": {
          "followers_count": 95,
          "following_count": 747,
          "like_count": 10336,
          "listed_count": 0,
          "media_count": 12,
          "tweet_count": 188
        },
        "url": "https://t.co/bm8bpeI3fN",
        "username": "seikuushona",
        "verified": false
      },
      {
        "created_at": "2023-06-07T02:52:39.000Z",
        "description": "有机化学，铁路，双偏同🌈，furry\n主要玩的游戏：彩虹六号围攻&PUBG\n爱国爱党🇨🇳 ，🙅鉴证\n白日梦想家，SIOC研0",
        "id": "1666276925474746371",
        "location": "舒服的被窝里",
        "name": "Jason",
        "profile_image_url": "https://pbs.twimg.com/profile_images/1729840885586882561/xRiyIr2W_normal.jpg",
        "protected": false,
        "public_metrics": {
          "followers_count": 37,
          "following_count": 331,
          "like_count": 190,
          "listed_count": 0,
          "media_count": 57,
          "tweet_count": 155
        },
        "url": "",
        "username": "Jason4028172723",
        "verified": false
      }
    ]
  }
}